matrix_cli/__init__.py
matrix_cli/__main__.py
matrix_cli/config.py
matrix_cli/health.py
matrix_cli/commands/alias.py
matrix_cli/commands/chat.py
matrix_cli/commands/connection.py
matrix_cli/commands/do.py
matrix_cli/commands/doctor.py
matrix_cli/commands/handle_url.py
matrix_cli/commands/help.py
matrix_cli/commands/install.py
matrix_cli/commands/link.py
matrix_cli/commands/logs.py
matrix_cli/commands/mcp.py
matrix_cli/commands/ps.py
matrix_cli/commands/remotes.py
matrix_cli/commands/resolution.py
matrix_cli/commands/run.py
matrix_cli/commands/search.py
matrix_cli/commands/show.py
matrix_cli/commands/stop.py
matrix_cli/commands/uninstall.py
matrix_cli/commands/version.py
matrix_cli/util/console.py
matrix_cli/util/tables.py
matrix_cli-0.1.8.dist-info/licenses/LICENSE
matrix_cli-0.1.8.dist-info/METADATA
matrix_cli-0.1.8.dist-info/WHEEL
matrix_cli-0.1.8.dist-info/entry_points.txt
matrix_cli-0.1.8.dist-info/top_level.txt
matrix_cli-0.1.8.dist-info/RECORD
