Metadata-Version: 2.4
Name: matrix-cli
Version: 0.1.8
Summary: Matrix CLI — thin UX layer over matrix-python-sdk (deep links, local builder, runtime)
Author-email: Ruslan Magana Vsevolodovna <contact@ruslanmv.com>
License-Expression: Apache-2.0
Project-URL: Homepage, https://matrixhub.io
Project-URL: Repository, https://github.com/agent-matrix/matrix-cli
Project-URL: Documentation, https://agent-matrix.github.io/matrix-cli/
Keywords: matrix,mcp,model context protocol,cli,agents,tools,runtime,search,installer
Classifier: Programming Language :: Python :: 3
Classifier: Programming Language :: Python :: 3 :: Only
Classifier: Programming Language :: Python :: 3.11
Classifier: Environment :: Console
Classifier: Intended Audience :: Developers
Classifier: Operating System :: OS Independent
Classifier: Topic :: Utilities
Classifier: Topic :: Software Development :: Libraries :: Application Frameworks
Classifier: Typing :: Typed
Requires-Python: >=3.11
License-File: LICENSE
Requires-Dist: typer>=0.12
Requires-Dist: rich>=13.7
Requires-Dist: matrix-python-sdk>=0.1.11
Requires-Dist: httpx<0.29,>=0.28
Requires-Dist: requests>=2.32
Requires-Dist: mcp>=1.13.1
Requires-Dist: websockets>=12.0
Provides-Extra: test
Requires-Dist: pytest>=8.0; extra == "test"
Requires-Dist: pytest-cov>=5.0; extra == "test"
Requires-Dist: pytest-mock>=3.14; extra == "test"
Provides-Extra: dev
Requires-Dist: pytest>=8.0; extra == "dev"
Requires-Dist: pytest-cov>=5.0; extra == "dev"
Requires-Dist: pytest-mock>=3.14; extra == "dev"
Requires-Dist: black>=24.0; extra == "dev"
Requires-Dist: ruff>=0.4; extra == "dev"
Requires-Dist: flake8>=7.0; extra == "dev"
Requires-Dist: mypy>=1.10; extra == "dev"
Requires-Dist: build>=1.2; extra == "dev"
Requires-Dist: twine>=5.0; extra == "dev"
Requires-Dist: mkdocs>=1.6; extra == "dev"
Requires-Dist: mkdocs-material>=9.5; extra == "dev"
Provides-Extra: mcp
Requires-Dist: mcp>=1.13.1; extra == "mcp"
Requires-Dist: websockets>=12.0; extra == "mcp"
Dynamic: license-file
